pybeamit/__init__.py
PyBeamIt-0.4.dist-info/METADATA
PyBeamIt-0.4.dist-info/WHEEL
PyBeamIt-0.4.dist-info/license
PyBeamIt-0.4.dist-info/top_level.txt
PyBeamIt-0.4.dist-info/RECORD
