Metadata-Version: 2.1
Name: PyBeamIt
Version: 0.4
Summary: python wrapper around the just beam it file sharing API
Home-page: http://github.com/cartertemm/pybeamit
Author: Carter Temm
Author-email: cartertemm@gmail.com
License: MIT
Platform: UNKNOWN
Classifier: Programming Language :: Python :: 3
Classifier: License :: OSI Approved :: MIT License
Classifier: Topic :: Communications :: File Sharing
Requires-Dist: requests
Requires-Dist: requests-toolbelt
